{
  "challengeList": [
    {
      "name": "5 under '5",
      "champs": [
        "CORKI",
        "FIZZ",
        "GNAR",
        "HEIMERDINGER",
        "KENNEN",
        "KLED",
        "LULU",
        "POPPY",
        "RUMBLE",
        "TEEMO",
        "TRISTANA",
        "VEIGAR",
        "VEX",
        "YUUMI",
        "ZIGGS"
      ]
    },
    {
      "name": "The Sun Disc Never Sets",
      "champs": [
        "AKSHAN",
        "AMUMU",
        "AZIR",
        "NASUS",
        "RAMMUS",
        "RENEKTON",
        "SIVIR",
        "SKARNER",
        "TALIYAH",
        "XERATH",
        "ZILEAN"
      ]
    },
    {
      "name": "All Hands On Deck",
      "champs": [
        "FIZZ",
        "GANGPLANK",
        "GRAVES",
        "ILLAOI",
        "MISS_FORTUNE",
        "NAUTILUS",
        "PYKE",
        "TAHM_KENCH",
        "TWISTED_FATE"
      ]
    },
    {
      "name": "FOR DEMACIA",
      "champs": [
        "FIORA",
        "GALIO",
        "GAREN",
        "JARVAN",
        "KAYLE",
        "LUCIAN",
        "LUX",
        "MORGANA",
        "POPPY",
        "QUINN",
        "SHYVANA",
        "SONA",
        "SYLAS",
        "VAYNE",
        "XIN_ZHAO"
      ]
    },
    {
      "name": "Ice, Ice, Baby",
      "champs": [
        "ANIVIA",
        "ASHE",
        "BRAUM",
        "GNAR",
        "GRAGAS",
        "LISSANDRA",
        "NUNU",
        "OLAF",
        "ORNN",
        "SEJUANI",
        "TRUNDLE",
        "TRYNDAMERE",
        "UDYR",
        "VOLIBEAR"
      ]
    },
    {
      "name": "Everybody was Wuju Fighting",
      "champs": [
        "AHRI",
        "AKALI",
        "IRELIA",
        "IVERN",
        "JHIN",
        "KARMA",
        "KAYN",
        "KENNEN",
        "LEE_SIN",
        "LILLIA",
        "MASTER_YI",
        "RAKAN",
        "SETT",
        "SHEN",
        "SYNDRA",
        "VARUS",
        "WUKONG",
        "XAYAH",
        "YASUO",
        "YONE",
        "ZED"
      ]
    },
    {
      "name": "Elemental, My Dear Watson",
      "champs": [
        "MALPHITE",
        "NEEKO",
        "NIDALEE",
        "QIYANA",
        "RENGAR",
        "ZYRA"
      ]
    },
    {
      "name": "Strength Above All",
      "champs": [
        "CASSIOPEIA",
        "DARIUS",
        "DRAVEN",
        "KATARINA",
        "KLED",
        "LEBLANC",
        "RELL",
        "RIVEN",
        "SAMIRA",
        "SION",
        "SWAIN",
        "TALON",
        "VLADIMIR"
      ]
    },
    {
      "name": "Calculated",
      "champs": [
        "CAITLYN",
        "CAMILLE",
        "CORKI",
        "EZREAL",
        "HEIMERDINGER",
        "JAYCE",
        "ORIANNA",
        "SERAPHINE",
        "VI"
      ]
    },
    {
      "name": "Spooky Scary Skeletons",
      "champs": [
        "ELISE",
        "EVELYNN",
        "FIDDLESTICKS",
        "GWEN",
        "HECARIM",
        "KALISTA",
        "KARTHUS",
        "MAOKAI",
        "SENNA",
        "THRESH",
        "VIEGO",
        "YORICK"
      ]
    },
    {
      "name": "Peak Performance",
      "champs": [
        "APHELIOS",
        "AURELION_SOL",
        "DIANA",
        "LEONA",
        "PANTHEON",
        "SORAKA",
        "TARIC",
        "ZOE"
      ]
    },
    {
      "name": "(Inhuman Screeching Sounds)",
      "champs": [
        "BELVETH",
        "CHOGATH",
        "KAISA",
        "KASSADIN",
        "KHAZIX",
        "KOGMAW",
        "MALZAHAR",
        "REKSAI",
        "VELKOZ"
      ]
    },
    {
      "name": "Chemtech Comrades",
      "champs": [
        "BLITZCRANK",
        "DR_MUNDO",
        "EKKO",
        "JANNA",
        "JINX",
        "RENATA_GLASC",
        "SINGED",
        "TWITCH",
        "URGOT",
        "VIKTOR",
        "WARWICK",
        "ZAC",
        "ZERI",
        "ZIGGS"
      ]
    },
    {
      "name": "It Has Ultimate In The Name",
      "champs": [
        "AMUMU",
        "ANIVIA",
        "ANNIE",
        "AURELION_SOL",
        "AZIR",
        "BARD",
        "BELVETH",
        "BLITZCRANK",
        "BRAUM",
        "CASSIOPEIA",
        "CORKI",
        "DIANA",
        "DRAVEN",
        "EKKO",
        "EVELYNN",
        "EZREAL",
        "FIDDLESTICKS",
        "FIZZ",
        "GALIO",
        "GANGPLANK",
        "GNAR",
        "GRAGAS",
        "GRAVES",
        "HECARIM",
        "HEIMERDINGER",
        "ILLAOI",
        "JANNA",
        "JARVAN",
        "JINX",
        "KARTHUS",
        "KATARINA",
        "KAYLE",
        "KENNEN",
        "LEONA",
        "LISSANDRA",
        "LUX",
        "MALPHITE",
        "MAOKAI",
        "MISS_FORTUNE",
        "MORGANA",
        "NAMI",
        "NEEKO",
        "NILAH",
        "NUNU",
        "ORIANNA",
        "ORNN",
        "PANTHEON",
        "QIYANA",
        "RAKAN",
        "RAMMUS",
        "RELL",
        "RENATA_GLASC",
        "RIVEN",
        "RUMBLE",
        "SAMIRA",
        "SEJUANI",
        "SENNA",
        "SERAPHINE",
        "SETT",
        "SONA",
        "SWAIN",
        "TALON",
        "TWITCH",
        "VELKOZ",
        "VIKTOR",
        "VLADIMIR",
        "VOLIBEAR",
        "XAYAH",
        "XIN_ZHAO",
        "YONE",
        "YUUMI",
        "ZAC",
        "ZERI",
        "ZIGGS",
        "ZYRA"
      ]
    },
    {
      "name": "Nowhere to Hide",
      "champs": [
        "AKSHAN",
        "ASHE",
        "BARD",
        "CAITLYN",
        "DRAVEN",
        "EZREAL",
        "GALIO",
        "GANGPLANK",
        "JHIN",
        "JINX",
        "KAISA",
        "KARTHUS",
        "KLED",
        "LILLIA",
        "LUX",
        "MAOKAI",
        "NOCTURNE",
        "PANTHEON",
        "RYZE",
        "SENNA",
        "SHEN",
        "SION",
        "SORAKA",
        "SWWAIN",
        "TALIYAH",
        "TWISTED_FATE",
        "VEX",
        "XERATH"
      ]
    },
    {
      "name": "We Protec",
      "champs": [
        "ALISTAR",
        "ANNIE",
        "BARD",
        "FIORA",
        "GALIO",
        "IVERN",
        "JANNA",
        "KARMA",
        "KAYLE",
        "KINDRED",
        "LEE_SIN",
        "LULU",
        "LUX",
        "MORGANA",
        "NAMI",
        "NIDALEE",
        "NILAH",
        "ORIANNA",
        "RAKAN",
        "RELL",
        "RENATA_GLASC",
        "SENNA",
        "SERAPHINE",
        "SHEN",
        "SONA",
        "SORAKA",
        "TAHM_KENCH",
        "TARIC",
        "THRESH",
        "YUUMI",
        "ZILEAN"
      ]
    },
    {
      "name": "I'm Helping",
      "champs": [
        "ANIVIA",
        "AZIR",
        "IRELIA",
        "IVERN",
        "JARVAN",
        "ORNN",
        "TALIYAH",
        "TRUNDLE",
        "VEIGAR",
        "YORICK"
      ]
    },
    {
      "name": "It's a Trap!",
      "champs": [
        "CAITLYN",
        "GANGPLANK",
        "JHIN",
        "JINX",
        "MAOKAI",
        "NIDALEE",
        "SHACO",
        "TEEMO",
        "ZIGGS",
        "ZYRA"
      ]
    },
    {
      "name": "Summoners on the Rift",
      "champs": [
        "ANNIE",
        "AZIR",
        "ELISE",
        "FIDDLESTICKS",
        "HEIMERDINGER",
        "ILLAOI",
        "IVERN",
        "KALISTA",
        "KINDRED",
        "LISSANDRA",
        "MALZAHAR",
        "MAOKAI",
        "NEEKO",
        "ORIANNA",
        "SHACO",
        "YORICK",
        "ZED",
        "ZYRA"
      ]
    },
    {
      "name": "Get Over Here",
      "champs": [
        "ALISTAR",
        "AURELION_SOL",
        "AZIR",
        "BLITZCRANK",
        "DARIUS",
        "GNAR",
        "GRAGAS",
        "HECARIM",
        "JANNA",
        "JAYCE",
        "KLED",
        "LEE_SIN",
        "MAOKAI",
        "MORDEKAISER",
        "NAUTILUS",
        "NILAH",
        "ORIANNA",
        "POPPY",
        "PYKE",
        "RELL",
        "SETT",
        "SINGED",
        "SKARNER",
        "SWAIN",
        "TAHM_KENCH",
        "TALIYAH",
        "THRESH",
        "TRISTANA",
        "URGOT",
        "VAYNE",
        "XIN_ZHAO",
        "YONE",
        "ZAC",
        "ZIGGS"
      ]
    },
    {
      "name": "We're Good Over Here",
      "champs": [
        "AKSHAN",
        "ASHE",
        "AZIR",
        "CAITLYN",
        "CHOGATH",
        "CORKI",
        "DR_MUNDO",
        "EZREAL",
        "GANGPLANK",
        "JAYCE",
        "JHIN",
        "JINX",
        "KAISA",
        "KARMA",
        "KLED",
        "KOGMAW",
        "LUX",
        "MAOKAI",
        "NIDALEE",
        "PANTHEON",
        "SENNA",
        "SERAPHINE",
        "SHYVANA",
        "SIVIR",
        "TALIYAH",
        "TWISTED_FATE",
        "VARUS",
        "VELKOZ",
        "VEX",
        "VIKTOR",
        "XAYAH",
        "XERATH",
        "YUUMI",
        "ZERI",
        "ZIGGS",
        "ZOE"
      ]
    },
    {
      "name": "Where'd They Go?",
      "champs": [
        "AKALI",
        "AKSHAN",
        "EVELYNN",
        "KAISA",
        "KHAZIX",
        "LEBLANC",
        "NEEKO",
        "NOCTURNE",
        "PYKE",
        "QIYANA",
        "RENGAR",
        "SENNA",
        "SHACO",
        "TALON",
        "TEEMO",
        "TWITCH",
        "VAYNE",
        "VIEGO"
      ]
    },
    {
      "name": "They Just Don't... Die!",
      "champs": [
        "AKSHAN",
        "ALISTAR",
        "ANIVIA",
        "BARD",
        "BELVETH",
        "BRAUM",
        "EKKO",
        "ELISE",
        "EVELYNN",
        "FIORA",
        "FIZZ",
        "GWEN",
        "JAX",
        "KALISTA",
        "KARTHUS",
        "KAYLE",
        "KAYN",
        "KINDRED",
        "KLED",
        "KOGMAW",
        "LISSANDRA",
        "MALZAHAR",
        "MAOKAI",
        "MASTER_YI",
        "OLAF",
        "PANTHEON",
        "RAKAN",
        "RENATA_GLASC",
        "SION",
        "TAHM_KENCH",
        "TARIC",
        "TRYNDAMERE",
        "VLADIMIR",
        "XIN_ZHAO",
        "YUUMI",
        "ZAC",
        "ZED",
        "ZILEAN"
      ]
    },
    {
      "name": "Hold That Pose",
      "champs": [
        "AATROX",
        "ALISTAR",
        "AMUMU",
        "ANIVIA",
        "AURELION_SOL",
        "BARD",
        "BLITZCRANK",
        "BRAUM",
        "CAMILLE",
        "GALIO",
        "GNAR",
        "GRAGAS",
        "HECARIM",
        "IVERN",
        "JANNA",
        "JARVAN",
        "KLED",
        "LEBLANC",
        "LEONA",
        "LISSANDRA",
        "LULU",
        "MAOKAI",
        "MORGANA",
        "NAMI",
        "NAUTILUS",
        "NEEKO",
        "NUNU",
        "ORNN",
        "POPPY",
        "PYKE",
        "QIYANA",
        "RAMMUS",
        "RELL",
        "RENATA_GLASC",
        "RIVEN",
        "SEJUANI",
        "SERAPHINE",
        "SETT",
        "SHACO",
        "SINGED",
        "SION",
        "SKARNER",
        "TAHM_KENCH",
        "THRESH",
        "URGOT",
        "VI",
        "WARWICK",
        "XIN_ZHAO",
        "YASUO",
        "YONE",
        "ZAC",
        "ZYRA"
      ]
    }
  ],
  "Champions": [
    "AATROX",
    "AHRI",
    "AKALI",
    "AKSHAN",
    "ALISTAR",
    "AMUMU",
    "ANIVIA",
    "ANNIE",
    "APHELIOS",
    "ASHE",
    "AURELION_SOL",
    "AZIR",
    "BARD",
    "BELVETH",
    "BLITZCRANK",
    "BRAND",
    "BRAUM",
    "CAITLYN",
    "CAMILLE",
    "CASSIOPEIA",
    "CHOGATH",
    "CORKI",
    "DARIUS",
    "DIANA",
    "DRAVEN",
    "DR_MUNDO",
    "EKKO",
    "ELISE",
    "EVELYNN",
    "EZREAL",
    "FIDDLESTICKS",
    "FIORA",
    "FIZZ",
    "GALIO",
    "GANGPLANK",
    "GAREN",
    "GNAR",
    "GRAGAS",
    "GRAVES",
    "GWEN",
    "HECARIM",
    "HEIMERDINGER",
    "ILLAOI",
    "IRELIA",
    "IVERN",
    "JANNA",
    "JARVAN",
    "JAX",
    "JAYCE",
    "JHIN",
    "JINX",
    "KAISA",
    "KALISTA",
    "KARMA",
    "KARTHUS",
    "KASSADIN",
    "KATARINA",
    "KAYLE",
    "KAYN",
    "KENNEN",
    "KHAZIX",
    "KINDRED",
    "KLED",
    "KOGMAW",
    "LEBLANC",
    "LEESIN",
    "LEONA",
    "LILLIA",
    "LISSANDRA",
    "LUCIAN",
    "LULU",
    "LUX",
    "MALPHITE",
    "MALZAHAR",
    "MAOKAI",
    "MASTER_YI",
    "MISS_FORTUNE",
    "MORDEKAISER",
    "MORGANA",
    "NAMI",
    "NASUS",
    "NAUTILUS",
    "NEEKO",
    "NIDALEE",
    "NILAH",
    "NOCTURNE",
    "NUNU",
    "OLAF",
    "ORIANNA",
    "ORNN",
    "PANTHEON",
    "POPPY",
    "PYKE",
    "QIYANA",
    "QUINN",
    "RAKAN",
    "RAMMUS",
    "REKSAI",
    "RELL",
    "RENATA",
    "RENEKTON",
    "RENGAR",
    "RIVEN",
    "RUMBLE",
    "RYZE",
    "SAMIRA",
    "SEJUANI",
    "SENNA",
    "SERAPHINE",
    "SETT",
    "SHACO",
    "SHEN",
    "SHYVANA",
    "SINGED",
    "SION",
    "SIVIR",
    "SKARNER",
    "SONA",
    "SORAKA",
    "SWAIN",
    "SYLAS",
    "SYNDRA",
    "TAHM_KENCH",
    "TALIYAH",
    "TALON",
    "TARIC",
    "TEEMO",
    "THRESH",
    "TRISTANA",
    "TRUNDLE",
    "TRYNDAMERE",
    "TWISTED_FATE",
    "TWITCH",
    "UDYR",
    "URGOT",
    "VARUS",
    "VAYNE",
    "VEIGAR",
    "VELKOZ",
    "VEX",
    "VI",
    "VIEGO",
    "VIKTOR",
    "VLADIMIR",
    "VOLIBEAR",
    "WARWICK",
    "WUKONG",
    "XAYAH",
    "XERATH",
    "XIN_ZHAO",
    "YASUO",
    "YONE",
    "YORICK",
    "YUUMI",
    "ZAC",
    "ZED",
    "ZERI",
    "ZIGGS",
    "ZILEAN",
    "ZOE",
    "ZYRA"
  ]
}